hafez/__init__.py
hafez/entry.py
hafez/data/hafez.json
hafez/data/audio/do_not_delete_me.txt
hafez/utils/__init__.py
hafez/utils/db.py
hafez/utils/formating.py
hafez-0.4.1.dist-info/licenses/LICENSE
hafez-0.4.1.dist-info/METADATA
hafez-0.4.1.dist-info/WHEEL
hafez-0.4.1.dist-info/top_level.txt
hafez-0.4.1.dist-info/RECORD
