Metadata-Version: 2.4
Name: hafez
Version: 0.4.1
Summary: Hafez Poems
Author-email: Kaveh Bakhtiyari <kbakhtiyari@yahoo.com>
Project-URL: Homepage, https://github.com/kavehbc/hafez
Project-URL: Bug Tracker, https://github.com/kavehbc/hafez
Classifier: Programming Language :: Python :: 3
Classifier: License :: OSI Approved :: MIT License
Classifier: Operating System :: OS Independent
Requires-Python: >=3.9
License-File: LICENSE
Dynamic: license-file
